odoo/addons/l10n_ro_stock_account/README.rst
odoo/addons/l10n_ro_stock_account/__init__.py
odoo/addons/l10n_ro_stock_account/__manifest__.py
odoo/addons/l10n_ro_stock_account/init_hook.py
odoo/addons/l10n_ro_stock_account/i18n/l10n_ro_stock_account.pot
odoo/addons/l10n_ro_stock_account/i18n/ro.po
odoo/addons/l10n_ro_stock_account/migrations/14.0.2.11.1/pre-migration.py
odoo/addons/l10n_ro_stock_account/migrations/14.0.2.7.1/post-migration.py
odoo/addons/l10n_ro_stock_account/migrations/14.0.2.8.1/pre-migration.py
odoo/addons/l10n_ro_stock_account/migrations/14.0.7.1.1/pre-migration.py
odoo/addons/l10n_ro_stock_account/migrations/14.0.8.0.0/pre-migration.py
odoo/addons/l10n_ro_stock_account/models/__init__.py
odoo/addons/l10n_ro_stock_account/models/account_account.py
odoo/addons/l10n_ro_stock_account/models/account_move.py
odoo/addons/l10n_ro_stock_account/models/product_category.py
odoo/addons/l10n_ro_stock_account/models/product_product.py
odoo/addons/l10n_ro_stock_account/models/product_template.py
odoo/addons/l10n_ro_stock_account/models/res_company.py
odoo/addons/l10n_ro_stock_account/models/stock_landed_cost.py
odoo/addons/l10n_ro_stock_account/models/stock_location.py
odoo/addons/l10n_ro_stock_account/models/stock_move.py
odoo/addons/l10n_ro_stock_account/models/stock_move_line.py
odoo/addons/l10n_ro_stock_account/models/stock_picking.py
odoo/addons/l10n_ro_stock_account/models/stock_quant.py
odoo/addons/l10n_ro_stock_account/models/stock_valuation_layer.py
odoo/addons/l10n_ro_stock_account/models/stock_valuation_layer_tracking.py
odoo/addons/l10n_ro_stock_account/readme/CONTRIBUTORS.rst
odoo/addons/l10n_ro_stock_account/readme/DESCRIPTION.rst
odoo/addons/l10n_ro_stock_account/security/ir.model.access.csv
odoo/addons/l10n_ro_stock_account/static/description/icon.png
odoo/addons/l10n_ro_stock_account/static/description/index.html
odoo/addons/l10n_ro_stock_account/tests/__init__.py
odoo/addons/l10n_ro_stock_account/tests/common.py
odoo14_addon_l10n_ro_stock_account-14.0.8.40.0.dist-info/METADATA
odoo14_addon_l10n_ro_stock_account-14.0.8.40.0.dist-info/WHEEL
odoo14_addon_l10n_ro_stock_account-14.0.8.40.0.dist-info/top_level.txt
odoo14_addon_l10n_ro_stock_account-14.0.8.40.0.dist-info/RECORD
